rest_framework_csv/__init__.py
rest_framework_csv/misc.py
rest_framework_csv/models.py
rest_framework_csv/orderedrows.py
rest_framework_csv/parsers.py
rest_framework_csv/py.typed
rest_framework_csv/renderers.py
rest_framework_csv/tests.py
rest_framework_csv/testfixtures/nonewlines.csv
djangorestframework_csv_3-3.0.0.dev1.dist-info/LICENSE
djangorestframework_csv_3-3.0.0.dev1.dist-info/METADATA
djangorestframework_csv_3-3.0.0.dev1.dist-info/WHEEL
djangorestframework_csv_3-3.0.0.dev1.dist-info/top_level.txt
djangorestframework_csv_3-3.0.0.dev1.dist-info/RECORD
