Metadata-Version: 2.1
Name: djangorestframework-csv-3
Version: 3.0.0.dev1
Summary: CSV Tools for Django REST Framework
Author-email: Mjumbe Wawatu Ukweli <mjumbewu@gmail.com>
Maintainer-email: Gabriel Dugny <git@dugny.me>
License: BSD
Project-URL: Homepage, https://github.com/GabDug/django-rest-framework-csv
Project-URL: Bug Tracker, https://github.com/GabDug/django-rest-framework-csv/issues
Classifier: Development Status :: 4 - Beta
Classifier: Environment :: Web Environment
Classifier: Intended Audience :: Developers
Classifier: License :: OSI Approved :: BSD License
Classifier: Operating System :: OS Independent
Classifier: Programming Language :: Python
Classifier: Programming Language :: Python :: 3
Classifier: Programming Language :: Python :: 3 :: Only
Classifier: Programming Language :: Python :: 3.8
Classifier: Programming Language :: Python :: 3.9
Classifier: Programming Language :: Python :: 3.10
Classifier: Programming Language :: Python :: 3.11
Classifier: Programming Language :: Python :: 3.12
Classifier: Framework :: Django
Classifier: Framework :: Django :: 3.2
Classifier: Framework :: Django :: 4.1
Classifier: Framework :: Django :: 4.2
Requires-Python: >=3.8
License-File: LICENSE
Requires-Dist: djangorestframework >=3.0.0
Requires-Dist: Django !=4.0.*,>=3.2
Requires-Dist: typing-extensions
